README.md
setup.py
duwi_smart_sdk/__init__.py
duwi_smart_sdk.egg-info/PKG-INFO
duwi_smart_sdk.egg-info/SOURCES.txt
duwi_smart_sdk.egg-info/dependency_links.txt
duwi_smart_sdk.egg-info/entry_points.txt
duwi_smart_sdk.egg-info/requires.txt
duwi_smart_sdk.egg-info/top_level.txt
duwi_smart_sdk/api/__init__.py
duwi_smart_sdk/api/account.py
duwi_smart_sdk/api/control.py
duwi_smart_sdk/api/discover.py
duwi_smart_sdk/api/floor.py
duwi_smart_sdk/api/house.py
duwi_smart_sdk/api/refresh_token.py
duwi_smart_sdk/api/room.py
duwi_smart_sdk/api/terminal.py
duwi_smart_sdk/api/ws.py
duwi_smart_sdk/const/__init__.py
duwi_smart_sdk/const/const.py
duwi_smart_sdk/const/status.py
duwi_smart_sdk/const/type_map.py
duwi_smart_sdk/model/__init__.py
duwi_smart_sdk/model/req/__init__.py
duwi_smart_sdk/model/req/device_control.py
duwi_smart_sdk/model/resp/__init__.py
duwi_smart_sdk/model/resp/auth.py
duwi_smart_sdk/model/resp/control.py
duwi_smart_sdk/model/resp/device.py
duwi_smart_sdk/model/resp/floor.py
duwi_smart_sdk/model/resp/house.py
duwi_smart_sdk/model/resp/room.py
duwi_smart_sdk/model/resp/terminal.py
duwi_smart_sdk/util/__init__.py
duwi_smart_sdk/util/http.py
duwi_smart_sdk/util/sign.py
duwi_smart_sdk/util/timestamp.py
test/__init__.py
test/api/__init__.py
test/api/test_account.py
test/api/test_control.py
test/api/test_discover.py
test/api/test_floor.py
test/api/test_house.py
test/api/test_login.py
test/api/test_room.py
test/api/test_terminal.py
test/api/test_ws.py
test/util/__init__.py
test/util/test_http.py